unihiker/Audio.py
unihiker/GUI.py
unihiker/HYQiHei_50S.ttf
unihiker/Segment7-4Gml.otf
unihiker/__init__.py
unihiker/emojis/Angry-1.png
unihiker/emojis/Angry-2.png
unihiker/emojis/Angry-3.png
unihiker/emojis/Angry-4.png
unihiker/emojis/Angry-5.png
unihiker/emojis/Nerve-1.png
unihiker/emojis/Nerve-2.png
unihiker/emojis/Nerve-3.png
unihiker/emojis/Nerve-4.png
unihiker/emojis/Nerve-5.png
unihiker/emojis/Peace-1.png
unihiker/emojis/Peace-2.png
unihiker/emojis/Peace-3.png
unihiker/emojis/Peace-4.png
unihiker/emojis/Peace-5.png
unihiker/emojis/Shock-1.png
unihiker/emojis/Shock-2.png
unihiker/emojis/Shock-3.png
unihiker/emojis/Shock-4.png
unihiker/emojis/Shock-5.png
unihiker/emojis/Sleep-1.png
unihiker/emojis/Sleep-2.png
unihiker/emojis/Sleep-3.png
unihiker/emojis/Sleep-4.png
unihiker/emojis/Sleep-5.png
unihiker/emojis/Smile-1.png
unihiker/emojis/Smile-2.png
unihiker/emojis/Smile-3.png
unihiker/emojis/Smile-4.png
unihiker/emojis/Smile-5.png
unihiker/emojis/Sweat-1.png
unihiker/emojis/Sweat-2.png
unihiker/emojis/Sweat-3.png
unihiker/emojis/Sweat-4.png
unihiker/emojis/Sweat-5.png
unihiker/emojis/Think-1.png
unihiker/emojis/Think-2.png
unihiker/emojis/Think-3.png
unihiker/emojis/Think-4.png
unihiker/emojis/Think-5.png
unihiker/emojis/Wink-1.png
unihiker/emojis/Wink-2.png
unihiker/emojis/Wink-3.png
unihiker/emojis/Wink-4.png
unihiker/emojis/Wink-5.png
unihiker-0.0.27.1.dist-info/LICENSE
unihiker-0.0.27.1.dist-info/METADATA
unihiker-0.0.27.1.dist-info/WHEEL
unihiker-0.0.27.1.dist-info/top_level.txt
unihiker-0.0.27.1.dist-info/RECORD
