Metadata-Version: 2.1
Name: unihiker
Version: 0.0.27.1
Summary: Library for Unihiker
Home-page: https://github.com/UNIHIKER/unihiker-pypi-lib
Author: Angelo Qiao, Raziur Totha
Author-email: angelo.qiao@dfrobot.com, raziur.totha@dfrobot.com
Project-URL: Bug Tracker, https://mc.dfrobot.com.cn/forum-221-1.html
Classifier: Programming Language :: Python :: 3
Classifier: License :: OSI Approved :: MIT License
Classifier: Operating System :: OS Independent
Classifier: Intended Audience :: Education
Classifier: Topic :: Software Development :: Libraries :: Python Modules
Requires-Python: >=3.6
License-File: LICENSE
Requires-Dist: fontTools
Requires-Dist: pillow
Requires-Dist: qrcode
Requires-Dist: pydub
Requires-Dist: pygame
Requires-Dist: pyaudio; platform_system == "Linux"
Requires-Dist: pyaudio; platform_system == "Windows"
